[{"pref":{"kana":"ｱｵﾓﾘｹﾝ","kanji":"青森県"},"address1":{"kana":"ﾋﾗｶﾜｼ","kanji":"平川市"},"address2":{"kana":"ｵｸﾞﾆｱｾｲｼﾔﾏ","kanji":"小国浅瀬石山"}},{"pref":{"kana":"ｱｵﾓﾘｹﾝ","kanji":"青森県"},"address1":{"kana":"ﾋﾗｶﾜｼ","kanji":"平川市"},"address2":{"kana":"ｵｸﾞﾆｶﾜﾍﾞ","kanji":"小国川辺"}},{"pref":{"kana":"ｱｵﾓﾘｹﾝ","kanji":"青森県"},"address1":{"kana":"ﾋﾗｶﾜｼ","kanji":"平川市"},"address2":{"kana":"ｵｸﾞﾆｶﾜﾗﾀﾞ","kanji":"小国川原田"}},{"pref":{"kana":"ｱｵﾓﾘｹﾝ","kanji":"青森県"},"address1":{"kana":"ﾋﾗｶﾜｼ","kanji":"平川市"},"address2":{"kana":"ｵｸﾞﾆﾌｶｻﾜ","kanji":"小国深沢"}},{"pref":{"kana":"ｱｵﾓﾘｹﾝ","kanji":"青森県"},"address1":{"kana":"ﾋﾗｶﾜｼ","kanji":"平川市"},"address2":{"kana":"ｵｸﾞﾆﾔﾏｼﾀ","kanji":"小国山下"}}]