[{"pref":{"kana":"ﾐﾔｷﾞｹﾝ","kanji":"宮城県"},"address1":{"kana":"ｲｸﾞｸﾞﾝﾏﾙﾓﾘﾏﾁ","kanji":"伊具郡丸森町"},"address2":{"kana":"ｲﾁｮｳ","kanji":"銀杏"}},{"pref":{"kana":"ﾐﾔｷﾞｹﾝ","kanji":"宮城県"},"address1":{"kana":"ｲｸﾞｸﾞﾝﾏﾙﾓﾘﾏﾁ","kanji":"伊具郡丸森町"},"address2":{"kana":"ｳｼﾛﾔｼｷ","kanji":"後屋敷"}},{"pref":{"kana":"ﾐﾔｷﾞｹﾝ","kanji":"宮城県"},"address1":{"kana":"ｲｸﾞｸﾞﾝﾏﾙﾓﾘﾏﾁ","kanji":"伊具郡丸森町"},"address2":{"kana":"ｺﾞﾌｸﾔ","kanji":"五福谷"}},{"pref":{"kana":"ﾐﾔｷﾞｹﾝ","kanji":"宮城県"},"address1":{"kana":"ｲｸﾞｸﾞﾝﾏﾙﾓﾘﾏﾁ","kanji":"伊具郡丸森町"},"address2":{"kana":"ｼﾀﾝﾀﾞ","kanji":"四反田"}},{"pref":{"kana":"ﾐﾔｷﾞｹﾝ","kanji":"宮城県"},"address1":{"kana":"ｲｸﾞｸﾞﾝﾏﾙﾓﾘﾏﾁ","kanji":"伊具郡丸森町"},"address2":{"kana":"ｼﾞｮｳﾁ","kanji":"上地"}},{"pref":{"kana":"ﾐﾔｷﾞｹﾝ","kanji":"宮城県"},"address1":{"kana":"ｲｸﾞｸﾞﾝﾏﾙﾓﾘﾏﾁ","kanji":"伊具郡丸森町"},"address2":{"kana":"ﾂｶﾀﾞ","kanji":"塚田"}},{"pref":{"kana":"ﾐﾔｷﾞｹﾝ","kanji":"宮城県"},"address1":{"kana":"ｲｸﾞｸﾞﾝﾏﾙﾓﾘﾏﾁ","kanji":"伊具郡丸森町"},"address2":{"kana":"ﾊﾞﾝｼﾞｮｳ","kanji":"坂上"}}]